README.txt
setup.py
collective/__init__.py
collective.multitemplate.egg-info/PKG-INFO
collective.multitemplate.egg-info/SOURCES.txt
collective.multitemplate.egg-info/dependency_links.txt
collective.multitemplate.egg-info/entry_points.txt
collective.multitemplate.egg-info/namespace_packages.txt
collective.multitemplate.egg-info/not-zip-safe
collective.multitemplate.egg-info/requires.txt
collective.multitemplate.egg-info/top_level.txt
collective/multitemplate/__init__.py
collective/multitemplate/configure.zcml
collective/multitemplate/portlet.py
docs/HISTORY.txt
docs/LICENSE.GPL
docs/LICENSE.txt