Metadata-Version: 1.0
Name: collective.multitemplate
Version: 1.0b1
Summary: UNKNOWN
Home-page: http://svn.plone.org/svn/collective/collective.multitemplate
Author: Jarn AS
Author-email: info@jarn.com
License: GPL
Platform: UNKNOWN
Classifier: Framework :: Plone
Classifier: Programming Language :: Python
Classifier: Topic :: Software Development :: Libraries :: Python Modules
